.gitignore
.readthedocs.yml
.travis.yml
MANIFEST.in
README.rst
pyproject.toml
setup.cfg
setup.py
tox.ini
docs/Makefile
docs/conf.py
docs/index.rst
docs/make.bat
docs/paper.bib
docs/paper.md
docs/linea/background.rst
docs/linea/eclipse.rst
docs/linea/index.rst
docs/linea/installation.rst
docs/linea/phasecurve.rst
example/55Cnce_build.ipynb
example/55Cnce_reduce.ipynb
example/WASP-189_build.ipynb
example/WASP-189_reduce.ipynb
licenses/LICENSE.rst
licenses/README.rst
licenses/TEMPLATE_LICENCE.rst
linea/__init__.py
linea/_astropy_init.py
linea/conftest.py
linea/core.py
linea/linalg.py
linea/planets.py
linea/version.py
linea.egg-info/PKG-INFO
linea.egg-info/SOURCES.txt
linea.egg-info/dependency_links.txt
linea.egg-info/not-zip-safe
linea.egg-info/requires.txt
linea.egg-info/top_level.txt
linea/data/README.rst
linea/data/example_55Cnce.fits
linea/data/example_wasp189_visit0.fits
linea/data/example_wasp189_visit1.fits
linea/data/example_wasp189_visit2.fits
linea/data/example_wasp189_visit3.fits
linea/data/planets.json
linea/tests/__init__.py
linea/tests/test_core_eclipse.py
linea/tests/test_core_phase_curve.py