Metadata-Version: 2.1
Name: linea
Version: 0.1
Summary: Linear detrending for CHEOPS
Home-page: https://github.com/bmorris3/linea
Author: Brett M. Morris
Author-email: morrisbrettm@gmail.com
License: BSD 3-Clause
Platform: UNKNOWN
Requires-Python: >=3.6
Provides-Extra: test
Provides-Extra: docs
